startinpy-0.12.2.dist-info/METADATA
startinpy-0.12.2.dist-info/WHEEL
startinpy-0.12.2.dist-info/license_files/LICENSE
startinpy/__init__.py
startinpy/startinpy.cp311-win_amd64.pyd
startinpy-0.12.2.dist-info/RECORD
