Metadata-Version: 2.3
Name: startinpy
Version: 0.12.2
Classifier: Programming Language :: Rust
Classifier: Programming Language :: Python :: Implementation :: CPython
Classifier: Programming Language :: Python :: Implementation :: PyPy
Requires-Dist: toml >=0.10.2
Requires-Dist: numpy >=1.24.0
License-File: LICENSE
Summary: Modelling terrains with Delaunay triangulation
Home-Page: https://github.com/hugoledoux/startinpy
Author: Hugo Ledoux <h.ledoux@tudelft.nl>
Author-email: Hugo Ledoux <h.ledoux@tudelft.nl>
License: MIT
Requires-Python: >=3.9
Project-URL: Source Code, https://github.com/hugoledoux/startinpy
